boviz/__init__.py
boviz/_version.py
boviz/cli.py
boviz/config.py
boviz/curves.py
boviz/heatmap.py
boviz/histogram.py
boviz/schematic.py
boviz/style.py
boviz/utils.py
boviz-0.3.3.dist-info/licenses/LICENSE
boviz-0.3.3.dist-info/METADATA
boviz-0.3.3.dist-info/WHEEL
boviz-0.3.3.dist-info/entry_points.txt
boviz-0.3.3.dist-info/top_level.txt
boviz-0.3.3.dist-info/RECORD
