Metadata-Version: 2.4
Name: boviz
Version: 0.3.3
Summary: An advanced and flexible scientific plotting toolkit.
Home-page: https://github.com/bo-qian/boviz
Author: Bo Qian
Author-email: Bo Qian <bqian@shu.edu.cn>
License: GNU General Public License v3 (GPLv3)
Project-URL: Homepage, https://github.com/bo-qian/boviz
Project-URL: Repository, https://github.com/bo-qian/boviz
Requires-Python: >=3.8
License-File: LICENSE
Requires-Dist: matplotlib>=3.0
Requires-Dist: numpy>=1.18
Requires-Dist: pandas>=1.0
Requires-Dist: pytest>=6.0
Requires-Dist: pathlib>=1.0
Requires-Dist: argparse>=1.4.0
Requires-Dist: meshio>=4.0
Requires-Dist: netCDF4>=1.5
Dynamic: author
Dynamic: home-page
Dynamic: license-file
Dynamic: requires-python
